pynyaa/__init__.py
pynyaa/_aclient.py
pynyaa/_client.py
pynyaa/_enums.py
pynyaa/_errors.py
pynyaa/_models.py
pynyaa/_parser.py
pynyaa/_utils.py
pynyaa/_version.py
pynyaa/py.typed
pynyaa-3.0.0.dist-info/METADATA
pynyaa-3.0.0.dist-info/WHEEL
pynyaa-3.0.0.dist-info/licenses/LICENSE
pynyaa-3.0.0.dist-info/RECORD
