Metadata-Version: 2.4
Name: pynyaa
Version: 3.0.0
Summary: Turn nyaa.si releases into neat Python objects.
Project-URL: Documentation, https://ravencentric.cc/pynyaa
Project-URL: Repository, https://github.com/Ravencentric/pynyaa
Author-email: Ravencentric <me@ravencentric.cc>
License-Expression: MIT
License-File: LICENSE
Keywords: anime,nyaa,nyaa.si,nyaasi,torrent
Classifier: Operating System :: OS Independent
Classifier: Programming Language :: Python :: 3.10
Classifier: Programming Language :: Python :: 3.11
Classifier: Programming Language :: Python :: 3.12
Classifier: Programming Language :: Python :: 3.13
Classifier: Typing :: Typed
Requires-Python: >=3.10
Requires-Dist: beautifulsoup4>=4.13.5
Requires-Dist: httpx>=0.27.2
